{
  "pisang": {
    "kode": "P001",
    "nama": "Pisang Ambon",
    "harga": 12000,
    "satuan": "/ kg",
    "promo": "Diskon 10%"
  },
  "mangga": {
    "kode": "P002",
    "nama": "Mangga Harum Manis",
    "harga": 15000,
    "satuan": "/ kg",
    "promo": ""
  },
  "telur": {
    "kode": "P003",
    "nama": "Telur Ayam Negeri",
    "harga": 20000,
    "satuan": "/ kg",
    "promo": "Beli 10 gratis 1"
  },
  "kopi": {
    "kode": "P004",
    "nama": "Kopi Bubuk Hitam",
    "harga": 18000,
    "satuan": "/ pack",
    "promo": ""
  },
  "beras": {
    "kode": "P005",
    "nama": "Beras Premium 5kg",
    "harga": 56500,
    "satuan": "/ pack",
    "promo": "Beli 2 Gratis Telur"
  },
  "gula": {
    "kode": "P006",
    "nama": "Gula Pasir Putih",
    "harga": 14500,
    "satuan": "/ kg",
    "promo": "Diskon 2.5%"
  },
  "susu": {
    "kode": "P007",
    "nama": "Susu Kental Manis",
    "harga": 24000,
    "satuan": "/ kaleng",
    "promo": "Beli 10 Gratis 1"
  },
  "teh": {
    "kode": "P008",
    "nama": "Teh Celup Wangi",
    "harga": 9000,
    "satuan": "/ kotak",
    "promo": ""
  }
}
